{
    "root": true,
    "labels": {
        "fi": "Kissasaari (saari)"
    },
    "descriptions": {
        "fi": "Keruukortti 1032, Saarijärvi, 1972"
    },
    "statements": {
        "instanceof": {
            "value": "entities/items/keruumerkinta"
        },
        "pitaja": {
            "value": "dataentities/pitaja/Saarijärvi"
        },
        "keruuhetki": {
            "value": {
                "time": "+1972-01-01T00:00:00Z",
                "timezone": 0,
                "before": 0,
                "after": 0,
                "precision": 9,
                "calendarmodel": "http://www.wikidata.org/entity/Q1985727"
            }
        },
        "keruukortintunnus": {
            "value": "1032"
        },
        "keruukortinkuva": {
            "value": "00000746_F.jpg"
        },
        "keruumerkinta": {
            "value": "Kissasaari"
        },
        "paikkatyyppi": {
            "value": "saari"
        },
        "karttaruutu-x": {
            "value": "65"
        },
        "karttaruutu-y": {
            "value": "65"
        },
        "keruumerkintakartalla": {
            "value": "5"
        },
        "keraaja": {
            "value": "dataentities/keraaja/Savolainen,_Irma"
        },
        "karttakuva": {
            "value": "dataentities/karttakuva/8892"
        },
        "coordinates": {
            "value": [
                62.77869692,
                25.286246174,
                1.0e-9
            ]
        }
    }
}