{
    "root": true,
    "labels": {
        "fi": "Pirttiniemi (niemi)"
    },
    "descriptions": {
        "fi": "Keruukortti 1581, Saarijärvi, 1965"
    },
    "statements": {
        "instanceof": {
            "value": "entities/items/keruumerkinta"
        },
        "pitaja": {
            "value": "dataentities/pitaja/Saarijärvi"
        },
        "keruuhetki": {
            "value": {
                "time": "+1965-01-01T00:00:00Z",
                "timezone": 0,
                "before": 0,
                "after": 0,
                "precision": 9,
                "calendarmodel": "http://www.wikidata.org/entity/Q1985727"
            }
        },
        "keruukortintunnus": {
            "value": "1581"
        },
        "keruukortinkuva": {
            "value": "00000756_F.jpg"
        },
        "keruumerkinta": {
            "value": "Pirttiniemi"
        },
        "paikkatyyppi": {
            "value": "niemi"
        },
        "karttaruutu-x": {
            "value": "4"
        },
        "karttaruutu-y": {
            "value": "A"
        },
        "keruumerkintakartalla": {
            "value": "3"
        },
        "keraaja": {
            "value": "dataentities/keraaja/Hakala,_Paavotapio"
        },
        "karttakuva": {
            "value": "dataentities/karttakuva/8878"
        },
        "coordinates": {
            "value": [
                62.642410723,
                25.430934298,
                1.0e-9
            ]
        }
    }
}