{
    "root": true,
    "labels": {
        "fi": "Pataminkorpi (mets채)"
    },
    "descriptions": {
        "fi": "Keruukortti 1061, Saarij채rvi, 1962"
    },
    "statements": {
        "instanceof": {
            "value": "entities/items/keruumerkinta"
        },
        "pitaja": {
            "value": "dataentities/pitaja/Saarij채rvi"
        },
        "keruuhetki": {
            "value": {
                "time": "+1962-01-01T00:00:00Z",
                "timezone": 0,
                "before": 0,
                "after": 0,
                "precision": 9,
                "calendarmodel": "http://www.wikidata.org/entity/Q1985727"
            }
        },
        "keruukortintunnus": {
            "value": "1061"
        },
        "keruukortinkuva": {
            "value": "00000236_F.jpg"
        },
        "keruumerkinta": {
            "value": "Pataminkorpi"
        },
        "paikkatyyppi": {
            "value": "mets채"
        },
        "karttaruutu-x": {
            "value": "6"
        },
        "karttaruutu-y": {
            "value": "T"
        },
        "keruumerkintakartalla": {
            "value": "4"
        },
        "keraaja": {
            "value": "dataentities/keraaja/Vesisenaho,_Kaisa"
        },
        "karttakuva": {
            "value": "dataentities/karttakuva/8876"
        },
        "coordinates": {
            "value": [
                62.734571964,
                24.990672427,
                1.0e-9
            ]
        }
    }
}