{
    "root": true,
    "labels": {
        "fi": "Kotikytö (pelto)"
    },
    "descriptions": {
        "fi": "Keruukortti 1562, Saarijärvi, 1973"
    },
    "statements": {
        "instanceof": {
            "value": "entities/items/keruumerkinta"
        },
        "pitaja": {
            "value": "dataentities/pitaja/Saarijärvi"
        },
        "keruuhetki": {
            "value": {
                "time": "+1973-01-01T00:00:00Z",
                "timezone": 0,
                "before": 0,
                "after": 0,
                "precision": 9,
                "calendarmodel": "http://www.wikidata.org/entity/Q1985727"
            }
        },
        "keruukortintunnus": {
            "value": "1562"
        },
        "keruukortinkuva": {
            "value": "00001276_F.jpg"
        },
        "keruumerkinta": {
            "value": "Kotikytö"
        },
        "paikkatyyppi": {
            "value": "pelto"
        },
        "karttaruutu-x": {
            "value": "75"
        },
        "karttaruutu-y": {
            "value": "66"
        },
        "keruumerkintakartalla": {
            "value": "6"
        },
        "keraaja": {
            "value": "dataentities/keraaja/Ollitervo,_Irma"
        },
        "karttakuva": {
            "value": "dataentities/karttakuva/8891"
        },
        "coordinates": {
            "value": [
                62.790039499,
                25.482152042,
                1.0e-9
            ]
        }
    }
}