{
    "root": true,
    "labels": {
        "fi": "Talaslahti (lahti)"
    },
    "descriptions": {
        "fi": "Keruukortti 441, Saarijärvi, 1972"
    },
    "statements": {
        "instanceof": {
            "value": "entities/items/keruumerkinta"
        },
        "pitaja": {
            "value": "dataentities/pitaja/Saarijärvi"
        },
        "keruuhetki": {
            "value": {
                "time": "+1972-01-01T00:00:00Z",
                "timezone": 0,
                "before": 0,
                "after": 0,
                "precision": 9,
                "calendarmodel": "http://www.wikidata.org/entity/Q1985727"
            }
        },
        "keruukortintunnus": {
            "value": "441"
        },
        "keruukortinkuva": {
            "value": "00000060_F.jpg"
        },
        "keruumerkinta": {
            "value": "Talaslahti"
        },
        "paikkatyyppi": {
            "value": "lahti"
        },
        "karttaruutu-x": {
            "value": "66"
        },
        "karttaruutu-y": {
            "value": "43"
        },
        "keruumerkintakartalla": {
            "value": "9"
        },
        "keraaja": {
            "value": "dataentities/keraaja/Rönnberg,_Aila"
        },
        "karttakuva": {
            "value": "dataentities/karttakuva/8885"
        },
        "coordinates": {
            "value": [
                62.592434735,
                25.287652691,
                1.0e-9
            ]
        }
    }
}