{
    "root": true,
    "labels": {
        "fi": "Kustu-rypysian mäki (mäki)"
    },
    "descriptions": {
        "fi": "Keruukortti 262, Saarijärvi, 1972"
    },
    "statements": {
        "instanceof": {
            "value": "entities/items/keruumerkinta"
        },
        "pitaja": {
            "value": "dataentities/pitaja/Saarijärvi"
        },
        "keruuhetki": {
            "value": {
                "time": "+1972-01-01T00:00:00Z",
                "timezone": 0,
                "before": 0,
                "after": 0,
                "precision": 9,
                "calendarmodel": "http://www.wikidata.org/entity/Q1985727"
            }
        },
        "keruukortintunnus": {
            "value": "262"
        },
        "keruukortinkuva": {
            "value": "00000262_F.jpg"
        },
        "keruumerkinta": {
            "value": "Kustu-rypysian mäki"
        },
        "paikkatyyppi": {
            "value": "mäki"
        },
        "karttaruutu-x": {
            "value": "66"
        },
        "karttaruutu-y": {
            "value": "44"
        },
        "keruumerkintakartalla": {
            "value": "12"
        },
        "keraaja": {
            "value": "dataentities/keraaja/Rönnberg,_Aila"
        },
        "karttakuva": {
            "value": "dataentities/karttakuva/8885"
        },
        "coordinates": {
            "value": [
                62.595171361,
                25.297159092,
                1.0e-9
            ]
        }
    }
}