{
    "root": true,
    "labels": {
        "fi": "Majatalo (pelto)"
    },
    "descriptions": {
        "fi": "Keruukortti 1273, Saarijärvi, 1976"
    },
    "statements": {
        "instanceof": {
            "value": "entities/items/keruumerkinta"
        },
        "pitaja": {
            "value": "dataentities/pitaja/Saarijärvi"
        },
        "keruuhetki": {
            "value": {
                "time": "+1976-01-01T00:00:00Z",
                "timezone": 0,
                "before": 0,
                "after": 0,
                "precision": 9,
                "calendarmodel": "http://www.wikidata.org/entity/Q1985727"
            }
        },
        "keruukortintunnus": {
            "value": "1273"
        },
        "keruukortinkuva": {
            "value": "00000047_F.jpg"
        },
        "keruumerkinta": {
            "value": "Majatalo"
        },
        "paikkatyyppi": {
            "value": "pelto"
        },
        "karttaruutu-x": {
            "value": "68"
        },
        "karttaruutu-y": {
            "value": "55"
        },
        "keruumerkintakartalla": {
            "value": "13"
        },
        "keraaja": {
            "value": "dataentities/keraaja/Ollitervo,_Irma"
        },
        "karttakuva": {
            "value": "dataentities/karttakuva/8893"
        },
        "coordinates": {
            "value": [
                62.696203524,
                25.326738879,
                1.0e-9
            ]
        }
    }
}