{
    "root": true,
    "labels": {
        "fi": "Honkamäki ()"
    },
    "descriptions": {
        "fi": "Keruukortti 1076, Saarijärvi, 1972"
    },
    "statements": {
        "instanceof": {
            "value": "entities/items/keruumerkinta"
        },
        "pitaja": {
            "value": "dataentities/pitaja/Saarijärvi"
        },
        "keruuhetki": {
            "value": {
                "time": "+1972-01-01T00:00:00Z",
                "timezone": 0,
                "before": 0,
                "after": 0,
                "precision": 9,
                "calendarmodel": "http://www.wikidata.org/entity/Q1985727"
            }
        },
        "keruukortintunnus": {
            "value": "1076"
        },
        "keruukortinkuva": {
            "value": "00000652_F.jpg"
        },
        "keruumerkinta": {
            "value": "Honkamäki"
        },
        "paikkatyyppi": {
            "value": null
        },
        "karttaruutu-x": {
            "value": null
        },
        "karttaruutu-y": {
            "value": null
        },
        "keruumerkintakartalla": {
            "value": null
        },
        "keraaja": {
            "value": "dataentities/keraaja/Rönnberg,_Aila"
        }
    }
}