{
    "root": true,
    "labels": {
        "fi": "Ostola (torppa)"
    },
    "descriptions": {
        "fi": "Keruukortti 629, Pylkönmäki, 1959"
    },
    "statements": {
        "instanceof": {
            "value": "entities/items/keruumerkinta"
        },
        "pitaja": {
            "value": "dataentities/pitaja/Pylkönmäki"
        },
        "keruuhetki": {
            "value": {
                "time": "+1959-01-01T00:00:00Z",
                "timezone": 0,
                "before": 0,
                "after": 0,
                "precision": 9,
                "calendarmodel": "http://www.wikidata.org/entity/Q1985727"
            }
        },
        "keruukortintunnus": {
            "value": "629"
        },
        "keruukortinkuva": {
            "value": "00000010_F.jpg"
        },
        "keruumerkinta": {
            "value": "Ostola"
        },
        "paikkatyyppi": {
            "value": "torppa"
        },
        "karttaruutu-x": {
            "value": "D"
        },
        "karttaruutu-y": {
            "value": "5"
        },
        "keruumerkintakartalla": {
            "value": "2"
        },
        "keraaja": {
            "value": "dataentities/keraaja/Paananen,_Unto"
        },
        "karttakuva": {
            "value": "dataentities/karttakuva/8358"
        },
        "coordinates": {
            "value": [
                62.706819879,
                24.861445207,
                1.0e-9
            ]
        }
    }
}